txl_editors/__init__.py
txl_editors/main.py
txl_editors-0.3.6.dist-info/METADATA
txl_editors-0.3.6.dist-info/WHEEL
txl_editors-0.3.6.dist-info/entry_points.txt
txl_editors-0.3.6.dist-info/licenses/LICENSE.txt
txl_editors-0.3.6.dist-info/RECORD
